{
  "annotations": {
    "list": [
      {
        "builtIn": 1,
        "datasource": {
          "type": "grafana",
          "uid": "-- Grafana --"
        },
        "enable": true,
        "hide": true,
        "iconColor": "rgba(0, 211, 255, 1)",
        "name": "Annotations & Alerts",
        "type": "dashboard"
      }
    ]
  },
  "editable": true,
  "fiscalYearStartMonth": 0,
  "graphTooltip": 0,
  "id": null,
  "links": [],
  "liveNow": false,
  "panels": [
    {
      "collapsed": false,
      "gridPos": {"h": 1, "w": 24, "x": 0, "y": 0},
      "id": 1,
      "panels": [],
      "title": "Service Overview",
      "type": "row"
    },
    {
      "datasource": {"type": "prometheus", "uid": "${datasource}"},
      "fieldConfig": {
        "defaults": {
          "color": {"mode": "thresholds"},
          "mappings": [],
          "thresholds": {
            "mode": "absolute",
            "steps": [
              {"color": "red", "value": null},
              {"color": "green", "value": 1}
            ]
          }
        },
        "overrides": []
      },
      "gridPos": {"h": 4, "w": 4, "x": 0, "y": 1},
      "id": 2,
      "options": {
        "colorMode": "background",
        "graphMode": "area",
        "justifyMode": "auto",
        "orientation": "auto",
        "reduceOptions": {
          "calcs": ["lastNotNull"],
          "fields": "",
          "values": false
        },
        "textMode": "auto"
      },
      "pluginVersion": "10.0.0",
      "targets": [
        {
          "expr": "up{job=\"user-service\"}",
          "refId": "A"
        }
      ],
      "title": "User Service",
      "type": "stat"
    },
    {
      "datasource": {"type": "prometheus", "uid": "${datasource}"},
      "fieldConfig": {
        "defaults": {
          "color": {"mode": "thresholds"},
          "mappings": [],
          "thresholds": {
            "mode": "absolute",
            "steps": [
              {"color": "red", "value": null},
              {"color": "green", "value": 1}
            ]
          }
        },
        "overrides": []
      },
      "gridPos": {"h": 4, "w": 4, "x": 4, "y": 1},
      "id": 3,
      "options": {
        "colorMode": "background",
        "graphMode": "area",
        "justifyMode": "auto",
        "orientation": "auto",
        "reduceOptions": {
          "calcs": ["lastNotNull"],
          "fields": "",
          "values": false
        },
        "textMode": "auto"
      },
      "pluginVersion": "10.0.0",
      "targets": [
        {
          "expr": "up{job=\"restaurant-service\"}",
          "refId": "A"
        }
      ],
      "title": "Restaurant Service",
      "type": "stat"
    },
    {
      "datasource": {"type": "prometheus", "uid": "${datasource}"},
      "fieldConfig": {
        "defaults": {
          "color": {"mode": "thresholds"},
          "mappings": [],
          "thresholds": {
            "mode": "absolute",
            "steps": [
              {"color": "red", "value": null},
              {"color": "green", "value": 1}
            ]
          }
        },
        "overrides": []
      },
      "gridPos": {"h": 4, "w": 4, "x": 8, "y": 1},
      "id": 4,
      "options": {
        "colorMode": "background",
        "graphMode": "area",
        "justifyMode": "auto",
        "orientation": "auto",
        "reduceOptions": {
          "calcs": ["lastNotNull"],
          "fields": "",
          "values": false
        },
        "textMode": "auto"
      },
      "pluginVersion": "10.0.0",
      "targets": [
        {
          "expr": "up{job=\"order-service\"}",
          "refId": "A"
        }
      ],
      "title": "Order Service",
      "type": "stat"
    },
    {
      "datasource": {"type": "prometheus", "uid": "${datasource}"},
      "fieldConfig": {
        "defaults": {
          "color": {"mode": "thresholds"},
          "mappings": [],
          "thresholds": {
            "mode": "absolute",
            "steps": [
              {"color": "red", "value": null},
              {"color": "green", "value": 1}
            ]
          }
        },
        "overrides": []
      },
      "gridPos": {"h": 4, "w": 4, "x": 12, "y": 1},
      "id": 5,
      "options": {
        "colorMode": "background",
        "graphMode": "area",
        "justifyMode": "auto",
        "orientation": "auto",
        "reduceOptions": {
          "calcs": ["lastNotNull"],
          "fields": "",
          "values": false
        },
        "textMode": "auto"
      },
      "pluginVersion": "10.0.0",
      "targets": [
        {
          "expr": "up{job=\"delivery-service\"}",
          "refId": "A"
        }
      ],
      "title": "Delivery Service",
      "type": "stat"
    },
    {
      "datasource": {"type": "prometheus", "uid": "${datasource}"},
      "fieldConfig": {
        "defaults": {
          "color": {"mode": "thresholds"},
          "mappings": [],
          "thresholds": {
            "mode": "absolute",
            "steps": [
              {"color": "red", "value": null},
              {"color": "green", "value": 1}
            ]
          }
        },
        "overrides": []
      },
      "gridPos": {"h": 4, "w": 4, "x": 16, "y": 1},
      "id": 6,
      "options": {
        "colorMode": "background",
        "graphMode": "area",
        "justifyMode": "auto",
        "orientation": "auto",
        "reduceOptions": {
          "calcs": ["lastNotNull"],
          "fields": "",
          "values": false
        },
        "textMode": "auto"
      },
      "pluginVersion": "10.0.0",
      "targets": [
        {
          "expr": "up{job=\"payment-service\"}",
          "refId": "A"
        }
      ],
      "title": "Payment Service",
      "type": "stat"
    },
    {
      "datasource": {"type": "prometheus", "uid": "${datasource}"},
      "fieldConfig": {
        "defaults": {
          "color": {"mode": "thresholds"},
          "mappings": [],
          "thresholds": {
            "mode": "absolute",
            "steps": [
              {"color": "red", "value": null},
              {"color": "green", "value": 1}
            ]
          }
        },
        "overrides": []
      },
      "gridPos": {"h": 4, "w": 4, "x": 20, "y": 1},
      "id": 20,
      "options": {
        "colorMode": "background",
        "graphMode": "area",
        "justifyMode": "auto",
        "orientation": "auto",
        "reduceOptions": {
          "calcs": ["lastNotNull"],
          "fields": "",
          "values": false
        },
        "textMode": "auto"
      },
      "pluginVersion": "10.0.0",
      "targets": [
        {
          "expr": "up{job=\"node-exporter\"}",
          "refId": "A"
        }
      ],
      "title": "Node Exporter",
      "type": "stat"
    },
    {
      "datasource": {"type": "prometheus", "uid": "${datasource}"},
      "fieldConfig": {
        "defaults": {
          "color": {"mode": "palette-classic"},
          "custom": {
            "axisCenteredZero": false,
            "axisColorMode": "text",
            "axisLabel": "",
            "axisPlacement": "auto",
            "barAlignment": 0,
            "drawStyle": "line",
            "fillOpacity": 10,
            "gradientMode": "none",
            "hideFrom": {"legend": false, "tooltip": false, "viz": false},
            "lineInterpolation": "linear",
            "lineWidth": 1,
            "pointSize": 5,
            "scaleDistribution": {"type": "linear"},
            "showPoints": "auto",
            "spanNulls": false,
            "stacking": {"group": "A", "mode": "none"},
            "thresholdsStyle": {"mode": "off"}
          },
          "mappings": [],
          "thresholds": {
            "mode": "absolute",
            "steps": [{"color": "green", "value": null}]
          },
          "unit": "reqps"
        },
        "overrides": []
      },
      "gridPos": {"h": 8, "w": 12, "x": 0, "y": 5},
      "id": 7,
      "options": {
        "legend": {"calcs": [], "displayMode": "list", "placement": "bottom", "showLegend": true},
        "tooltip": {"mode": "single", "sort": "none"}
      },
      "pluginVersion": "10.0.0",
      "targets": [
        {
          "expr": "sum by (job) (rate(http_requests_total[1m]))",
          "legendFormat": "{{job}}",
          "refId": "A"
        }
      ],
      "title": "Request Rate (req/s)",
      "type": "timeseries"
    },
    {
      "datasource": {"type": "prometheus", "uid": "${datasource}"},
      "fieldConfig": {
        "defaults": {
          "color": {"mode": "palette-classic"},
          "custom": {
            "axisCenteredZero": false,
            "axisColorMode": "text",
            "axisLabel": "",
            "axisPlacement": "auto",
            "barAlignment": 0,
            "drawStyle": "line",
            "fillOpacity": 10,
            "gradientMode": "none",
            "hideFrom": {"legend": false, "tooltip": false, "viz": false},
            "lineInterpolation": "linear",
            "lineWidth": 1,
            "pointSize": 5,
            "scaleDistribution": {"type": "linear"},
            "showPoints": "auto",
            "spanNulls": false,
            "stacking": {"group": "A", "mode": "none"},
            "thresholdsStyle": {"mode": "off"}
          },
          "mappings": [],
          "thresholds": {
            "mode": "absolute",
            "steps": [{"color": "red", "value": null}, {"color": "green", "value": 0.95}]
          },
          "unit": "percentunit"
        },
        "overrides": []
      },
      "gridPos": {"h": 8, "w": 12, "x": 12, "y": 5},
      "id": 8,
      "options": {
        "legend": {"calcs": [], "displayMode": "list", "placement": "bottom", "showLegend": true},
        "tooltip": {"mode": "single", "sort": "none"}
      },
      "pluginVersion": "10.0.0",
      "targets": [
        {
          "expr": "sum by (job) (rate(http_requests_total{status!~\"5..\"}[1m])) / sum by (job) (rate(http_requests_total[1m]))",
          "legendFormat": "{{job}}",
          "refId": "A"
        }
      ],
      "title": "Success Rate (%)",
      "type": "timeseries"
    },
    {
      "datasource": {"type": "prometheus", "uid": "${datasource}"},
      "fieldConfig": {
        "defaults": {
          "color": {"mode": "palette-classic"},
          "custom": {
            "axisCenteredZero": false,
            "axisColorMode": "text",
            "axisLabel": "",
            "axisPlacement": "auto",
            "barAlignment": 0,
            "drawStyle": "line",
            "fillOpacity": 10,
            "gradientMode": "none",
            "hideFrom": {"legend": false, "tooltip": false, "viz": false},
            "lineInterpolation": "linear",
            "lineWidth": 1,
            "pointSize": 5,
            "scaleDistribution": {"type": "linear"},
            "showPoints": "auto",
            "spanNulls": false,
            "stacking": {"group": "A", "mode": "none"},
            "thresholdsStyle": {"mode": "off"}
          },
          "mappings": [],
          "thresholds": {
            "mode": "absolute",
            "steps": [{"color": "green", "value": null}, {"color": "yellow", "value": 0.1}, {"color": "red", "value": 0.5}]
          },
          "unit": "s"
        },
        "overrides": []
      },
      "gridPos": {"h": 8, "w": 12, "x": 0, "y": 13},
      "id": 9,
      "options": {
        "legend": {"calcs": [], "displayMode": "list", "placement": "bottom", "showLegend": true},
        "tooltip": {"mode": "single", "sort": "none"}
      },
      "pluginVersion": "10.0.0",
      "targets": [
        {
          "expr": "histogram_quantile(0.95, sum by (le, job) (rate(http_request_duration_seconds_bucket[1m])))",
          "legendFormat": "p95 {{job}}",
          "refId": "A"
        },
        {
          "expr": "histogram_quantile(0.50, sum by (le, job) (rate(http_request_duration_seconds_bucket[1m])))",
          "legendFormat": "p50 {{job}}",
          "refId": "B"
        }
      ],
      "title": "Request Latency (p50, p95)",
      "type": "timeseries"
    },
    {
      "datasource": {"type": "prometheus", "uid": "${datasource}"},
      "fieldConfig": {
        "defaults": {
          "color": {"mode": "palette-classic"},
          "custom": {
            "axisCenteredZero": false,
            "axisColorMode": "text",
            "axisLabel": "",
            "axisPlacement": "auto",
            "barAlignment": 0,
            "drawStyle": "line",
            "fillOpacity": 10,
            "gradientMode": "none",
            "hideFrom": {"legend": false, "tooltip": false, "viz": false},
            "lineInterpolation": "linear",
            "lineWidth": 1,
            "pointSize": 5,
            "scaleDistribution": {"type": "linear"},
            "showPoints": "auto",
            "spanNulls": false,
            "stacking": {"group": "A", "mode": "none"},
            "thresholdsStyle": {"mode": "off"}
          },
          "mappings": [],
          "thresholds": {
            "mode": "absolute",
            "steps": [{"color": "green", "value": null}]
          },
          "unit": "bytes"
        },
        "overrides": []
      },
      "gridPos": {"h": 8, "w": 12, "x": 12, "y": 13},
      "id": 10,
      "options": {
        "legend": {"calcs": [], "displayMode": "list", "placement": "bottom", "showLegend": true},
        "tooltip": {"mode": "single", "sort": "none"}
      },
      "pluginVersion": "10.0.0",
      "targets": [
        {
          "expr": "process_resident_memory_bytes",
          "legendFormat": "{{job}}",
          "refId": "A"
        }
      ],
      "title": "Memory Usage (App)",
      "type": "timeseries"
    },
    {
      "collapsed": false,
      "gridPos": {"h": 1, "w": 24, "x": 0, "y": 21},
      "id": 30,
      "panels": [],
      "title": "Host System Metrics (Node Exporter)",
      "type": "row"
    },
    {
      "datasource": {"type": "prometheus", "uid": "${datasource}"},
      "fieldConfig": {
        "defaults": {
          "color": {"mode": "palette-classic"},
          "custom": {
            "axisCenteredZero": false,
            "axisColorMode": "text",
            "axisLabel": "",
            "axisPlacement": "auto",
            "barAlignment": 0,
            "drawStyle": "line",
            "fillOpacity": 10,
            "gradientMode": "none",
            "hideFrom": {"legend": false, "tooltip": false, "viz": false},
            "lineInterpolation": "linear",
            "lineWidth": 1,
            "pointSize": 5,
            "scaleDistribution": {"type": "linear"},
            "showPoints": "auto",
            "spanNulls": false,
            "stacking": {"group": "A", "mode": "none"},
            "thresholdsStyle": {"mode": "off"}
          },
          "mappings": [],
          "thresholds": {
            "mode": "absolute",
            "steps": [{"color": "green", "value": null}, {"color": "yellow", "value": 0.7}, {"color": "red", "value": 0.9}]
          },
          "unit": "percentunit"
        },
        "overrides": []
      },
      "gridPos": {"h": 8, "w": 12, "x": 0, "y": 22},
      "id": 31,
      "options": {
        "legend": {"calcs": [], "displayMode": "list", "placement": "bottom", "showLegend": true},
        "tooltip": {"mode": "single", "sort": "none"}
      },
      "pluginVersion": "10.0.0",
      "targets": [
        {
          "expr": "100 - (avg by (instance) (irate(node_cpu_seconds_total{mode=\"idle\"}[5m])) * 100)",
          "legendFormat": "CPU % ({{instance}})",
          "refId": "A"
        }
      ],
      "title": "Host CPU Usage",
      "type": "timeseries"
    },
    {
      "datasource": {"type": "prometheus", "uid": "${datasource}"},
      "fieldConfig": {
        "defaults": {
          "color": {"mode": "palette-classic"},
          "custom": {
            "axisCenteredZero": false,
            "axisColorMode": "text",
            "axisLabel": "",
            "axisPlacement": "auto",
            "barAlignment": 0,
            "drawStyle": "line",
            "fillOpacity": 10,
            "gradientMode": "none",
            "hideFrom": {"legend": false, "tooltip": false, "viz": false},
            "lineInterpolation": "linear",
            "lineWidth": 1,
            "pointSize": 5,
            "scaleDistribution": {"type": "linear"},
            "showPoints": "auto",
            "spanNulls": false,
            "stacking": {"group": "A", "mode": "none"},
            "thresholdsStyle": {"mode": "off"}
          },
          "mappings": [],
          "thresholds": {
            "mode": "absolute",
            "steps": [{"color": "green", "value": null}, {"color": "yellow", "value": 0.7}, {"color": "red", "value": 0.9}]
          },
          "unit": "percentunit"
        },
        "overrides": []
      },
      "gridPos": {"h": 8, "w": 12, "x": 12, "y": 22},
      "id": 32,
      "options": {
        "legend": {"calcs": [], "displayMode": "list", "placement": "bottom", "showLegend": true},
        "tooltip": {"mode": "single", "sort": "none"}
      },
      "pluginVersion": "10.0.0",
      "targets": [
        {
          "expr": "(1 - (node_memory_MemAvailable_bytes / node_memory_MemTotal_bytes)) * 100",
          "legendFormat": "Memory % ({{instance}})",
          "refId": "A"
        }
      ],
      "title": "Host Memory Usage",
      "type": "timeseries"
    },
    {
      "datasource": {"type": "prometheus", "uid": "${datasource}"},
      "fieldConfig": {
        "defaults": {
          "color": {"mode": "palette-classic"},
          "custom": {
            "axisCenteredZero": false,
            "axisColorMode": "text",
            "axisLabel": "",
            "axisPlacement": "auto",
            "barAlignment": 0,
            "drawStyle": "line",
            "fillOpacity": 10,
            "gradientMode": "none",
            "hideFrom": {"legend": false, "tooltip": false, "viz": false},
            "lineInterpolation": "linear",
            "lineWidth": 1,
            "pointSize": 5,
            "scaleDistribution": {"type": "linear"},
            "showPoints": "auto",
            "spanNulls": false,
            "stacking": {"group": "A", "mode": "none"},
            "thresholdsStyle": {"mode": "off"}
          },
          "mappings": [],
          "thresholds": {
            "mode": "absolute",
            "steps": [{"color": "green", "value": null}, {"color": "yellow", "value": 70}, {"color": "red", "value": 90}]
          },
          "unit": "percentunit"
        },
        "overrides": []
      },
      "gridPos": {"h": 8, "w": 12, "x": 0, "y": 30},
      "id": 33,
      "options": {
        "legend": {"calcs": [], "displayMode": "list", "placement": "bottom", "showLegend": true},
        "tooltip": {"mode": "single", "sort": "none"}
      },
      "pluginVersion": "10.0.0",
      "targets": [
        {
          "expr": "100 - ((node_filesystem_avail_bytes{mountpoint=\"/\"} * 100) / node_filesystem_size_bytes{mountpoint=\"/\"})",
          "legendFormat": "Disk % ({{instance}})",
          "refId": "A"
        }
      ],
      "title": "Host Disk Usage",
      "type": "timeseries"
    },
    {
      "datasource": {"type": "prometheus", "uid": "${datasource}"},
      "fieldConfig": {
        "defaults": {
          "color": {"mode": "palette-classic"},
          "custom": {
            "axisCenteredZero": false,
            "axisColorMode": "text",
            "axisLabel": "",
            "axisPlacement": "auto",
            "barAlignment": 0,
            "drawStyle": "line",
            "fillOpacity": 10,
            "gradientMode": "none",
            "hideFrom": {"legend": false, "tooltip": false, "viz": false},
            "lineInterpolation": "linear",
            "lineWidth": 1,
            "pointSize": 5,
            "scaleDistribution": {"type": "linear"},
            "showPoints": "auto",
            "spanNulls": false,
            "stacking": {"group": "A", "mode": "none"},
            "thresholdsStyle": {"mode": "off"}
          },
          "mappings": [],
          "thresholds": {
            "mode": "absolute",
            "steps": [{"color": "green", "value": null}]
          },
          "unit": "Bps"
        },
        "overrides": []
      },
      "gridPos": {"h": 8, "w": 12, "x": 12, "y": 30},
      "id": 34,
      "options": {
        "legend": {"calcs": [], "displayMode": "list", "placement": "bottom", "showLegend": true},
        "tooltip": {"mode": "single", "sort": "none"}
      },
      "pluginVersion": "10.0.0",
      "targets": [
        {
          "expr": "irate(node_network_receive_bytes_total{device!~\"lo\"}[5m])",
          "legendFormat": "RX {{device}} ({{instance}})",
          "refId": "A"
        },
        {
          "expr": "irate(node_network_transmit_bytes_total{device!~\"lo\"}[5m])",
          "legendFormat": "TX {{device}} ({{instance}})",
          "refId": "B"
        }
      ],
      "title": "Host Network I/O",
      "type": "timeseries"
    },
    {
      "collapsed": false,
      "gridPos": {"h": 1, "w": 24, "x": 0, "y": 38},
      "id": 11,
      "panels": [],
      "title": "Logs",
      "type": "row"
    },
    {
      "datasource": {"type": "loki", "uid": "${loki_datasource}"},
      "gridPos": {"h": 8, "w": 24, "x": 0, "y": 39},
      "id": 12,
      "options": {
        "showTime": true,
        "sortOrder": "Descending",
        "wrapLogMessage": true,
        "prettifyLogMessage": true,
        "enableLogDetails": true,
        "dedupStrategy": "none"
      },
      "pluginVersion": "10.0.0",
      "targets": [
        {
          "expr": "{job=\"zomato-services\"} |~ \".*ERROR.*|.*error.*|.*Error.*\"",
          "refId": "A",
          "editorMode": "builder"
        }
      ],
      "title": "Error Logs (All Services)",
      "type": "logs"
    }
  ],
  "refresh": "10s",
  "schemaVersion": 38,
  "style": "dark",
  "tags": ["microservices", "zomato-clone"],
  "templating": {
    "list": [
      {
        "current": {
          "selected": false,
          "text": "Prometheus",
          "value": "Prometheus"
        },
        "hide": 0,
        "includeAll": false,
        "label": "Datasource",
        "multi": false,
        "name": "datasource",
        "options": [],
        "query": "prometheus",
        "refresh": 1,
        "regex": "",
        "skipUrlSync": false,
        "type": "datasource"
      },
      {
        "current": {
          "selected": false,
          "text": "Loki",
          "value": "Loki"
        },
        "hide": 0,
        "includeAll": false,
        "label": "Loki Datasource",
        "multi": false,
        "name": "loki_datasource",
        "options": [],
        "query": "loki",
        "refresh": 1,
        "regex": "",
        "skipUrlSync": false,
        "type": "datasource"
      }
    ]
  },
  "time": {"from": "now-15m", "to": "now"},
  "timepicker": {},
  "timezone": "browser",
  "title": "Zomato Clone - Microservices Overview",
  "uid": "zomato-microservices",
  "version": 1,
  "weekStart": ""
}
